{
  "start": {
    "character": "pink",
    "txt": "Alright, this should be far enough.",
     "next": "d2"
  },
  "d2": {
    "character": "pink",
    "txt": "How are you feeling?",
    "choices": [
      { "label": "I'm fine.", "next": "fine" },
      { "label": "What just happened?", "next": "what" }
    ]   
  },
  "fine": {
    "character": "pink",
    "txt": "Good! I was worried you would be hurt. Then who would take the blame for crashing the ship? Haha!",
    "next": "fine2"
  },
  "fine2": {
    "character": "pink",
    "txt": "It's a good thing we got away from the crash site. Don't want to be around if the ship decides to blow up or something.",
    "next": "fine3"
  },
  "fine3": {
    "character": "pink",
    "txt": "We do need to find a way to fix the ship though...",
    "next": "anyway"
  },
  "what": {
    "character": "pink",
    "txt": "Seems like the engine took a hit.",
    "next": "what2"
  },
  "what2": {
    "character": "pink",
    "txt": "I think that's what caused the crash.",
    "next": "what3"
  },
  "what3": {
    "character": "pink",
    "txt": "We need to stay away from the ship until we can fix it. It might not be safe here.",
    "next": "anyway"
  },
  "anyway": {
    "character": "pink",
    "txt": "Anyway, since we got away from the crash site, we should look around.",
    "next": "anyway2"
  },
  "anyway2": {
    "character": "pink",
    "txt": "There's a clearing up ahead, let's try there first.",
    "next": "scene4"
  }
}
