{
  "pink": {
    "name": "Pink",
    "voice": "voice.ogg",
    "portrait": "pink_image"
  },
  "owlet": {
    "name": "Owlet",
    "voice": "voice2.ogg",
    "portrait": "owlet_image"
  },
  "player": {
    "name": "player",
    "voice": "voice3.ogg",
    "portrait": "dude_image"
  },
  "Mechanic": {
    "name": "Mechanic",
    "portrait": "mechanic_image"
  },
  "wraith_01": {
    "name": "Wraith",
    "portrait": "wraith_01_image"
  },
  "wraith_03": {
    "name": "Elder Wraith",
    "portrait": "wraith_03_image"
  }
}